tastytrade_mcp/__init__.py
tastytrade_mcp/__main__.py
tastytrade_mcp/cli.py
tastytrade_mcp/main.py
tastytrade_mcp/api/accounts.py
tastytrade_mcp/api/app.py
tastytrade_mcp/api/auth.py
tastytrade_mcp/api/balances.py
tastytrade_mcp/api/health.py
tastytrade_mcp/api/helpers.py
tastytrade_mcp/api/market_data.py
tastytrade_mcp/api/orders.py
tastytrade_mcp/api/positions.py
tastytrade_mcp/api/sandbox.py
tastytrade_mcp/auth/jwt_service.py
tastytrade_mcp/auth/oauth_config.py
tastytrade_mcp/auth/oauth_service.py
tastytrade_mcp/config/__init__.py
tastytrade_mcp/config/constants.py
tastytrade_mcp/config/emergency_state.json
tastytrade_mcp/config/settings.py
tastytrade_mcp/config/settings_comprehensive.py
tastytrade_mcp/config/user_shortcuts.json
tastytrade_mcp/core/__init__.py
tastytrade_mcp/core/base_handler.py
tastytrade_mcp/core/dispatcher.py
tastytrade_mcp/core/handler_factory.py
tastytrade_mcp/core/service_registry.py
tastytrade_mcp/db/__init__.py
tastytrade_mcp/db/base.py
tastytrade_mcp/db/engine.py
tastytrade_mcp/db/session.py
tastytrade_mcp/db/setup.py
tastytrade_mcp/handlers/__init__.py
tastytrade_mcp/handlers/accounts.py
tastytrade_mcp/handlers/accounts_oauth.py
tastytrade_mcp/handlers/accounts_simple.py
tastytrade_mcp/handlers/advanced_market_oauth.py
tastytrade_mcp/handlers/advanced_positions_oauth.py
tastytrade_mcp/handlers/analysis.py
tastytrade_mcp/handlers/analysis_oauth.py
tastytrade_mcp/handlers/auth_router.py
tastytrade_mcp/handlers/emergency_oauth.py
tastytrade_mcp/handlers/handler_adapter.py
tastytrade_mcp/handlers/health.py
tastytrade_mcp/handlers/help.py
tastytrade_mcp/handlers/market_data_oauth.py
tastytrade_mcp/handlers/option_chain_oauth.py
tastytrade_mcp/handlers/position_handlers.py
tastytrade_mcp/handlers/positions_oauth.py
tastytrade_mcp/handlers/realtime_quotes_oauth.py
tastytrade_mcp/handlers/registry.py
tastytrade_mcp/handlers/router.py
tastytrade_mcp/handlers/shortcuts.py
tastytrade_mcp/handlers/simple_option_quotes.py
tastytrade_mcp-1.4.3.dist-info/licenses/LICENSE
tastytrade_mcp-1.4.3.dist-info/METADATA
tastytrade_mcp-1.4.3.dist-info/WHEEL
tastytrade_mcp-1.4.3.dist-info/entry_points.txt
tastytrade_mcp-1.4.3.dist-info/top_level.txt
tastytrade_mcp-1.4.3.dist-info/RECORD
