Metadata-Version: 2.4
Name: tastytrade-mcp
Version: 1.4.3
Summary: TastyTrade MCP Server - Production-ready OAuth trading with full instrument support
Author: TastyTrade MCP Team
License: MIT
Project-URL: Homepage, https://github.com/tastytrade/tastytrade-mcp
Project-URL: Documentation, https://github.com/tastytrade/tastytrade-mcp/blob/main/README.md
Project-URL: Repository, https://github.com/tastytrade/tastytrade-mcp
Project-URL: Issues, https://github.com/tastytrade/tastytrade-mcp/issues
Keywords: tastytrade,mcp,trading,claude,chatgpt,api
Classifier: Development Status :: 5 - Production/Stable
Classifier: Intended Audience :: Financial and Insurance Industry
Classifier: License :: OSI Approved :: MIT License
Classifier: Programming Language :: Python :: 3
Classifier: Programming Language :: Python :: 3.8
Classifier: Programming Language :: Python :: 3.9
Classifier: Programming Language :: Python :: 3.10
Classifier: Programming Language :: Python :: 3.11
Classifier: Programming Language :: Python :: 3.12
Classifier: Topic :: Office/Business :: Financial :: Investment
Classifier: Topic :: Software Development :: Libraries :: Python Modules
Requires-Python: >=3.8
License-File: LICENSE
Requires-Dist: click>=8.0.0
Requires-Dist: fastapi>=0.104.0
Requires-Dist: uvicorn[standard]>=0.24.0
Requires-Dist: pydantic>=2.0.0
Requires-Dist: httpx>=0.25.0
Requires-Dist: python-dotenv>=1.0.0
Requires-Dist: tastytrade>=8.0.0
Requires-Dist: mcp>=1.0.0
Requires-Dist: cryptography>=41.0.0
Requires-Dist: sqlalchemy>=2.0.0
Requires-Dist: greenlet>=2.0.0
Requires-Dist: aiosqlite>=0.19.0
Requires-Dist: alembic>=1.12.0
Requires-Dist: typer>=0.9.0
Requires-Dist: rich>=13.0.0
Requires-Dist: psutil>=5.9.0
Requires-Dist: redis>=5.0.0
Provides-Extra: dev
Requires-Dist: pytest>=7.0.0; extra == "dev"
Requires-Dist: pytest-cov>=4.0.0; extra == "dev"
Requires-Dist: black>=23.0.0; extra == "dev"
Requires-Dist: ruff>=0.1.0; extra == "dev"
Requires-Dist: mypy>=1.0.0; extra == "dev"
Requires-Dist: pre-commit>=3.0.0; extra == "dev"
Dynamic: license-file
